forg/__init__.py
forg/filesext.py
forg/forg.py
forg/data/__init__.py
forg/data/filesext.csv
forg-1.4.0.dist-info/LICENSE
forg-1.4.0.dist-info/METADATA
forg-1.4.0.dist-info/WHEEL
forg-1.4.0.dist-info/entry_points.txt
forg-1.4.0.dist-info/top_level.txt
forg-1.4.0.dist-info/RECORD
