Metadata-Version: 2.1
Name: forg
Version: 1.4.0
Summary: 🗂 File Organizer - forg
Home-page: https://github.com/rqfreitas/forg
Author: rqfreitas
Author-email: mail@rqf.fr
License: UNKNOWN
Project-URL: Bug Tracker, https://github.com/rqfreitas/forg/issues
Platform: UNKNOWN
Classifier: Programming Language :: Python :: 3
Classifier: License :: OSI Approved :: MIT License
Classifier: Operating System :: OS Independent
Requires-Python: >=3.6
